dorest/__init__.py
dorest/conf.py
dorest/decorators.py
dorest/exceptions.py
dorest/glossary.py
dorest/interfaces.py
dorest/meta.py
dorest/packages.py
dorest/permissions.py
dorest/resources.py
dorest/struct.py
dorest/verbose.py
dorest-0.1.2.dist-info/LICENSE
dorest-0.1.2.dist-info/METADATA
dorest-0.1.2.dist-info/WHEEL
dorest-0.1.2.dist-info/top_level.txt
dorest-0.1.2.dist-info/RECORD
