Metadata-Version: 2.1
Name: dorest
Version: 0.1.2
Summary: API manager extension for Django REST Framework
Home-page: https://github.com/rungsiman/dorest
Author-email: rungsiman@gmail.com
License: UNKNOWN
Platform: UNKNOWN
Classifier: Programming Language :: Python :: 3
Classifier: License :: OSI Approved :: BSD License
Classifier: Operating System :: OS Independent
Requires-Python: >=3.6
